{"stats":{"minecraft:custom":{"minecraft:open_barrel":1,"minecraft:time_since_rest":6318,"minecraft:crouch_one_cm":12494,"minecraft:sprint_one_cm":662090,"minecraft:play_time":68927,"minecraft:deaths":39,"minecraft:damage_taken":45930,"minecraft:walk_one_cm":73395,"minecraft:sneak_time":3723,"minecraft:walk_under_water_one_cm":5187,"minecraft:jump":1927,"minecraft:minecart_one_cm":11117,"minecraft:damage_dealt":254,"minecraft:leave_game":1,"minecraft:walk_on_water_one_cm":11645,"minecraft:time_since_death":6315,"minecraft:climb_one_cm":7551,"minecraft:total_world_time":68927,"minecraft:swim_one_cm":6236,"minecraft:target_hit":4,"minecraft:fall_one_cm":157115,"minecraft:fly_one_cm":558954,"minecraft:player_kills":3},"minecraft:killed_by":{"minecraft:creeper":16,"minecraft:player":4},"minecraft:used":{"minecraft:snowball":5}},"DataVersion":3953}